Workbook

Sheet Valuation
B1: FY 24 | C1: FY25E | D1: FY26E | E1: FY27E | F1: FY28E | G1: FY29E | H1: FY30E | I1: FY31E | J1: FY32E | L1: Tax Rate | M1: 0.25
B2: 0 | C2: 1 | D2: 2 | E2: 3 | F2: 4 | G2: 5 | H2: 6 | I2: 7 | J2: 8 | L2: WACC | M2: =WACC!F7 -> 0.090262332
A3: EBIT * (1-t) | B3: ='Financial Statements'!E151*(1-0.25) -> 459066 | C3: ='Financial Statements'!F151*(1-0.25) -> 609358.95 | D3: ='Financial Statements'!G151*(1-0.25) -> 665961.27 | E3: ='Financial Statements'!H151*(1-0.25) -> 721866.45 | F3: ='Financial Statements'!I151*(1-0.25) -> 775340.78 | G3: ='Financial Statements'!J151*(1-0.25) -> 825945.58 | H3: ='Financial Statements'!K151*(1-0.25) -> 879129.22 | I3: ='Financial Statements'!L151*(1-0.25) -> 927075.27 | J3: ='Financial Statements'!M151*(1-0.25) -> 976690.53 | L3: Long Term Growth Rate | M3: ='Revenue Prediction'!M3 -> 0.053518047
A4: Add: Depreciation
A5: Depreciation of Tangible Assets | B5: ='Financial Statements'!E92 -> 93420 | C5: ='Financial Statements'!F92 -> 93420 | D5: ='Financial Statements'!G92 -> 119312.15 | E5: ='Financial Statements'!H92 -> 143381.29 | F5: ='Financial Statements'!I92 -> 166019.29 | G5: ='Financial Statements'!J92 -> 187382.84 | H5: ='Financial Statements'!K92 -> 207554.97 | I5: ='Financial Statements'!L92 -> 227035.01 | J5: ='Financial Statements'!M92 -> 245573.16
A6: Depreciation of Intangible Assets | B6: ='Financial Statements'!E94 -> 41154 | C6: ='Financial Statements'!F94 -> 41154 | D6: ='Financial Statements'!G94 -> 44067.39 | E6: ='Financial Statements'!H94 -> 47259.352 | F6: ='Financial Statements'!I94 -> 50723.705 | G6: ='Financial Statements'!J94 -> 54445.01 | H6: ='Financial Statements'!K94 -> 58405.604 | I6: ='Financial Statements'!L94 -> 62617.249 | J6: ='Financial Statements'!M94 -> 67049.613
A7: Depreciation of Rights-of-Use Assets | B7: ='Financial Statements'!E96 -> 75921 | C7: ='Financial Statements'!F96 -> 75921 | D7: ='Financial Statements'!G96 -> 60132.511 | E7: ='Financial Statements'!H96 -> 47627.388 | F7: ='Financial Statements'!I96 -> 37722.823 | G7: ='Financial Statements'!J96 -> 29878.006 | H7: ='Financial Statements'!K96 -> 23664.593 | I7: ='Financial Statements'!L96 -> 18743.317 | J7: ='Financial Statements'!M96 -> 14845.468
A8: Amortization of R&D Asset | B8: ='CapEx Readjustments'!E13 -> 0 | C8: ='CapEx Readjustments'!F13 -> 21676.312 | D8: ='CapEx Readjustments'!G13 -> 27021.983 | E8: ='CapEx Readjustments'!H13 -> 32031.155 | F8: ='CapEx Readjustments'!I13 -> 36775.637 | G8: ='CapEx Readjustments'!J13 -> 41278.66 | H8: ='CapEx Readjustments'!K13 -> 45549.897 | I8: ='CapEx Readjustments'!L13 -> 49692.85 | J8: ='CapEx Readjustments'!M13 -> 53647.065
A9: Total Depreciation | B9: =SUM(B5:B8) -> 210495 | C9: =SUM(C5:C8) -> 232171.31 | D9: =SUM(D5:D8) -> 250534.03 | E9: =SUM(E5:E8) -> 270299.18 | F9: =SUM(F5:F8) -> 291241.45 | G9: =SUM(G5:G8) -> 312984.51 | H9: =SUM(H5:H8) -> 335175.07 | I9: =SUM(I5:I8) -> 358088.43 | J9: =SUM(J5:J8) -> 381115.31
A10: Less: Change in Non-Cash WC | B10: =-'Financial Statements'!E116 -> -41231 | C10: =-'Financial Statements'!F116 -> -80889.163 | D10: =-'Financial Statements'!G116 -> -29108.143 | E10: =-'Financial Statements'!H116 -> -28749.638 | F10: =-'Financial Statements'!I116 -> -27499.553 | G10: =-'Financial Statements'!J116 -> -26023.877 | H10: =-'Financial Statements'!K116 -> -27350.064 | I10: =-'Financial Statements'!L116 -> -24656.6 | J10: =-'Financial Statements'!M116 -> -25514.998
A11: Less: Capital Expenditure
A12: Puchase of Property, Plant & Equipment | B12: ='Financial Statements'!E119 -> -190919 | C12: ='Financial Statements'!F119 -> -198838.91 | D12: ='Financial Statements'!G119 -> -217308.72 | E12: ='Financial Statements'!H119 -> -235551.05 | F12: ='Financial Statements'!I119 -> -253000.17 | G12: ='Financial Statements'!J119 -> -269512.94 | H12: ='Financial Statements'!K119 -> -286867.2 | I12: ='Financial Statements'!L119 -> -302512.4 | J12: ='Financial Statements'!M119 -> -318702.28
A13: Business Combinations | B13: ='Financial Statements'!E124 -> -265288 | C13: ='Financial Statements'!F124 -> -374283.12 | D13: ='Financial Statements'!G124 -> -409049.64 | E13: ='Financial Statements'!H124 -> -443387.97 | F13: ='Financial Statements'!I124 -> -476233.2 | G13: ='Financial Statements'!J124 -> -507315.9 | H13: ='Financial Statements'!K124 -> -539982.59 | I13: ='Financial Statements'!L124 -> -569432.23 | J13: ='Financial Statements'!M124 -> -599907.13
A14: Investment in R&D Asset | B14: ='Financial Statements'!E127 -> 0 | C14: ='Financial Statements'!F127 -> -43058.993 | D14: ='Financial Statements'!G127 -> -47058.67 | E14: ='Financial Statements'!H127 -> -51009.085 | F14: ='Financial Statements'!I127 -> -54787.73 | G14: ='Financial Statements'!J127 -> -58363.605 | H14: ='Financial Statements'!K127 -> -62121.709 | I14: ='Financial Statements'!L127 -> -65509.71 | J14: ='Financial Statements'!M127 -> -69015.662
A15: Total Capital Expenditure | B15: =SUM(B12:B14) -> -456207 | C15: =SUM(C12:C14) -> -616181.02 | D15: =SUM(D12:D14) -> -673417.03 | E15: =SUM(E12:E14) -> -729948.1 | F15: =SUM(F12:F14) -> -784021.1 | G15: =SUM(G12:G14) -> -835192.45 | H15: =SUM(H12:H14) -> -888971.51 | I15: =SUM(I12:I14) -> -937454.34 | J15: =SUM(J12:J14) -> -987625.07
A16: FCFF | B16: =B3+B9+B10+B15 -> 172123 | C16: =C3+C9+C10+C15 -> 144460.07 | D16: =D3+D9+D10+D15 -> 213970.13 | E16: =E3+E9+E10+E15 -> 233467.89 | F16: =F3+F9+F10+F15 -> 255061.57 | G16: =G3+G9+G10+G15 -> 277713.76 | H16: =H3+H9+H10+H15 -> 297982.72 | I16: =I3+I9+I10+I15 -> 323052.76 | J16: =J3+J9+J10+J15 -> 344665.78 | K16: =J16*(1+M3) -> 363111.62
A17: Terminal Value | J17: =K16/(M2-M3) -> 9882125
A18: PV of FCFF | C18: =C16/((1+$M$2)^C2) -> 132500.29 | D18: =D16/((1+$M$2)^D2) -> 180007.72 | E18: =E16/((1+$M$2)^E2) -> 180149.94 | F18: =F16/((1+$M$2)^F2) -> 180518.2 | G18: =G16/((1+$M$2)^G2) -> 180277.85 | H18: =H16/((1+$M$2)^H2) -> 177421 | I18: =I16/((1+$M$2)^I2) -> 176423.49 | J18: =SUM(J16:J17)/((1+$M$2)^J2) -> 5122610.2
A20: Value of Operating Assets | B20: =B16+SUM(C18:J18) -> 6502031.7 | J20: All figures in millions

Sheet Revenue Prediction
B1: 2021 | C1: 2022 | D1: 2023 | E1: 2024 | F1: 2025 | G1: 2026 | H1: 2027 | I1: 2028 | J1: 2029 | K1: 2030 | L1: 2031 | M1: 2032
A2: Puig Total Revenue | B2: 2585012 | C2: 3619603 | D2: 4304067 | E2: 4789779 | F2: =SUM(F6:F8) -> 5200171.5 | G2: =SUM(G6:G8) -> 5683206.6 | H2: =SUM(H6:H8) -> 6160292.5 | I2: =SUM(I6:I8) -> 6616633.9 | J2: =SUM(J6:J8) -> 7048487.1 | K2: =SUM(K6:K8) -> 7502347.7 | L2: =SUM(L6:L8) -> 7911511.7 | M2: =SUM(M6:M8) -> 8334920.4
A3: Revenue Growth % | C3: =C2/B2-1 -> 0.40022677 | D3: =D2/C2-1 -> 0.18909919 | E3: =E2/D2-1 -> 0.11284954 | F3: =F2/E2-1 -> 0.085680893 | G3: =G2/F2-1 -> 0.0928883 | H3: =H2/G2-1 -> 0.083946601 | I3: =I2/H2-1 -> 0.07407787 | J3: =J2/I2-1 -> 0.065267816 | ... M3: =M2/L2-1 -> 0.053518047
A5: Revenues by Geography
A6: EMEA | B6: 1498000 | C6: 1959900 | D6: 2322116 | E6: 2620004 | F6: =E6*(1+F11) -> 2882004.4 | G6: =F6*(1+G11) -> 3141384.8 | H6: =G6*(1+H11) -> 3392695.6 | I6: =H6*(1+I11) -> 3630184.3 | J6: =I6*(1+J11) -> 3847995.3 | K6: =J6*(1+K11) -> 4078875 | L6: =K6*(1+L11) -> 4282818.8 | M6: =L6*(1+M11) -> 4496959.7
A7: Americas | B7: 839000 | C7: 1311900 | D7: 1542978 | E7: 1714634 | F7: =E7*(1+F12) -> 1817512 | G7: =F7*(1+G12) -> 1981088.1 | H7: =G7*(1+H12) -> 2139575.2 | I7: =H7*(1+I12) -> 2289345.4 | J7: =I7*(1+J12) -> 2426706.2 | K7: =J7*(1+K12) -> 2572308.5 | L7: =K7*(1+L12) -> 2700924 | M7: =L7*(1+M12) -> 2835970.2
A8: APAC | B8: 248100 | C8: 347800 | D8: 438973 | E8: 455141 | F8: =E8*(1+F13) -> 500655.1 | G8: =F8*(1+G13) -> 560733.71 | H8: =G8*(1+H13) -> 628021.76 | I8: =H8*(1+I13) -> 697104.15 | J8: =I8*(1+J13) -> 773785.61 | K8: =J8*(1+K13) -> 851164.17 | L8: =K8*(1+L13) -> 927768.94 | M8: =L8*(1+M13) -> 1001990.5
A10: % YOY Growth
A11: EMEA | C11: =C6/B6-1 -> 0.30834446 | D11: =D6/C6-1 -> 0.18481351 | E11: =E6/D6-1 -> 0.128283 | F11: 0.1 | G11: 0.09 | H11: 0.08 | I11: 0.07 | J11: 0.06 | K11: 0.06 | L11: 0.05 | M11: 0.05
A12: Americas | C12: =C7/B7-1 -> 0.5636472 | D12: =D7/C7-1 -> 0.17613995 | E12: =E7/D7-1 -> 0.1112498 | F12: 0.06 | G12: 0.09 | H12: 0.08 | I12: 0.07 | J12: 0.06 | K12: 0.06 | L12: 0.05 | M12: 0.05
A13: APAC | C13: =C8/B8-1 -> 0.40185409 | D13: =D8/C8-1 -> 0.26214204 | E13: =E8/D8-1 -> 0.036831422 | F13: 0.1 | G13: 0.12 | H13: 0.12 | I13: 0.11 | J13: 0.11 | K13: 0.1 | L13: 0.09 | M13: 0.08
A15: % Share per Geography
A16: EMEA | B16: =B6/B$2 -> 0.57949441 | C16: =C6/C$2 -> 0.54146822 | D16: =D6/D$2 -> 0.53951669 | E16: =E6/E$2 -> 0.54699893 | F16: =F6/F$2 -> 0.55421333 | G16: =G6/G$2 -> 0.55274865 | H16: =H6/H$2 -> 0.55073612 | I16: =I6/I$2 -> 0.54864518 | ... M16: =M6/M$2 -> 0.53953242
A17: Americas | B17: =B7/B$2 -> 0.32456329 | C17: =C7/C$2 -> 0.36244306 | D17: =D7/D$2 -> 0.35849303 | E17: =E7/E$2 -> 0.35797769 | F17: =F7/F$2 -> 0.34951002 | G17: =G7/G$2 -> 0.34858633 | H17: =H7/H$2 -> 0.34731714 | I17: =I7/I$2 -> 0.34599851 | ... M17: =M7/M$2 -> 0.34025162
A18: APAC | B18: =B8/B$2 -> 0.095976344 | C18: =C8/C$2 -> 0.096087886 | D18: =D8/D$2 -> 0.10199028 | E18: =E8/E$2 -> 0.095023382 | F18: =F8/F$2 -> 0.096276651 | G18: =G8/G$2 -> 0.098665023 | H18: =H8/H$2 -> 0.10194674 | I18: =I8/I$2 -> 0.10535631 | ... M18: =M8/M$2 -> 0.12021596
M20: Calculations
M21: Historical Data
M22: Assumptions
M24: All figures in million euros

Sheet Financial Statements
B1: FY21 | C1: FY22 | D1: FY23 | E1: FY24 | F1: FY25E | G1: FY26E | H1: FY27E | I1: FY28E | J1: FY29E | K1: FY30E | L1: FY31E | M1: FY32E
A2: Net Revenues | B2: 2585012 | C2: 3619603 | D2: 4304067 | E2: 4789779 | F2: {='Revenue Prediction'!F2:M2} -> 5200171.5 | G2: 5683206.6 | H2: 6160292.5 | I2: 6616633.9 | J2: 7048487.1 | K2: 7502347.7 | L2: 7911511.7 | M2: 8334920.4
A3: % Change | C3: =C2/B2-1 -> 0.40022677 | D3: =D2/C2-1 -> 0.18909919 | E3: =E2/D2-1 -> 0.11284954 | F3: =F2/E2-1 -> 0.085680893 | G3: =G2/F2-1 -> 0.0928883 | H3: =H2/G2-1 -> 0.083946601 | I3: =I2/H2-1 -> 0.07407787 | J3: =J2/I2-1 -> 0.065267816 | ... M3: =M2/L2-1 -> 0.053518047
A4: Less: Cost of Sales | B4: 699906 | C4: 926969 | D4: 1088904 | E4: 1201679 | F4: =F2*F5 -> 1304639.9 | G4: =G2*G5 -> 1425825.7 | H4: =H2*H5 -> 1545518.9 | I4: =I2*I5 -> 1660007.7 | J4: =J2*J5 -> 1768352.8 | K4: =K2*K5 -> 1882219.1 | L4: =L2*L5 -> 1984871.8 | M4: =M2*M5 -> 2091098.3
A5: % of Revenue | B5: =B4/B2 -> 0.27075542 | C5: =C4/C2 -> 0.25609687 | D5: =D4/D2 -> 0.2529942 | E5: =E4/E2 -> 0.25088402 | F5: =E5 -> 0.25088402 | G5: =F5 -> 0.25088402 | H5: =G5 -> 0.25088402 | I5: =H5 -> 0.25088402 | J5: =I5 -> 0.25088402 | K5: =J5 -> 0.25088402 | L5: =K5 -> 0.25088402 | M5: =L5 -> 0.25088402
A6: Gross Profit | B6: =B2-B4 -> 1885106 | C6: =C2-C4 -> 2692634 | D6: =D2-D4 -> 3215163 | E6: =E2-E4 -> 3588100 | F6: =F2-F4 -> 3895531.6 | G6: =G2-G4 -> 4257380.9 | H6: =H2-H4 -> 4614773.6 | I6: =I2-I4 -> 4956626.2 | ... M6: =M2-M4 -> 6243822
A7: % Change | C7: =C6/B6-1 -> 0.42837273 | D7: =D6/C6-1 -> 0.19405868 | E7: =E6/D6-1 -> 0.11599319 | F7: =F6/E6-1 -> 0.085680893 | G7: =G6/F6-1 -> 0.0928883 | H7: =H6/G6-1 -> 0.083946601 | I7: =I6/H6-1 -> 0.07407787 | J7: =J6/I6-1 -> 0.065267816 | ... M7: =M6/L6-1 -> 0.053518047
A8: Less:
A9: Distribution Expense | B9: 138235 | C9: 221663 | D9: 217685 | E9: 220384 | F9: =F2*F10 -> 239266.7 | G9: =G2*G10 -> 261491.77 | H9: =H2*H10 -> 283443.12 | I9: =I2*I10 -> 304439.98 | J9: =J2*J10 -> 324310.12 | K9: =K2*K10 -> 345192.84 | L9: =L2*L10 -> 364019.01 | M9: =M2*M10 -> 383500.59
A10: % of Revenue | B10: =B9/B$2 -> 0.053475574 | C10: =C9/C$2 -> 0.061239589 | D10: =D9/D$2 -> 0.050576583 | E10: =E9/E$2 -> 0.046011309 | F10: =E10 -> 0.046011309 | G10: =F10 -> 0.046011309 | H10: =G10 -> 0.046011309 | I10: =H10 -> 0.046011309 | J10: =I10 -> 0.046011309 | K10: =J10 -> 0.046011309 | L10: =K10 -> 0.046011309 | M10: =L10 -> 0.046011309
A11: Advertising & Promotion Expenses | B11: 838962 | C11: 1099676 | D11: 1338144 | E11: 1551285 | F11: =F2*F12 -> 1642131 | G11: =G2*G12 -> 1794665.8 | H11: =H2*H12 -> 1945321.9 | I11: =I2*I12 -> 2089427.2 | J11: =J2*J12 -> 2225799.5 | K11: =K2*K12 -> 2369121.5 | L11: =L2*L12 -> 2498328.9 | M11: =M2*M12 -> 2632034.6
A12: % of Revenue | B12: =B11/B$2 -> 0.32454859 | C12: =C11/C$2 -> 0.30381122 | D12: =D11/D$2 -> 0.31090222 | E12: =E11/E$2 -> 0.32387402 | F12: =AVERAGE(B12:E12) -> 0.31578401 | G12: =F12 -> 0.31578401 | H12: =G12 -> 0.31578401 | I12: =H12 -> 0.31578401 | J12: =I12 -> 0.31578401 | K12: =J12 -> 0.31578401 | L12: =K12 -> 0.31578401 | M12: =L12 -> 0.31578401
A13: Selling, General & Administrative Expenses | B13: 556331 | C13: 834800 | D13: 966364 | E13: 1057717 | F13: =F2*F14 -> 1158596.3 | G13: =G2*G14 -> 1266216.3 | H13: =H2*H14 -> 1372510.9 | I13: =I2*I14 -> 1474183.6 | J13: =J2*J14 -> 1570400.3 | K13: =K2*K14 -> 1671520.3 | L13: =L2*L14 -> 1762681.9 | M13: =M2*M14 -> 1857017.1
A14: % of Revenue | B14: =B13/B$2 -> 0.21521409 | C14: =C13/C$2 -> 0.23063303 | D14: =D13/D$2 -> 0.22452346 | E14: =E13/E$2 -> 0.22082793 | F14: =AVERAGE(B14:E14) -> 0.22279963 | G14: =F14 -> 0.22279963 | H14: =G14 -> 0.22279963 | I14: =H14 -> 0.22279963 | J14: =I14 -> 0.22279963 | K14: =J14 -> 0.22279963 | L14: =K14 -> 0.22279963 | M14: =L14 -> 0.22279963
A16: Total Expenditure except Cost of Sales | B16: =B13+B11+B9 -> 1533528 | C16: =C13+C11+C9 -> 2156139 | D16: =D13+D11+D9 -> 2522193 | E16: =E13+E11+E9 -> 2829386 | F16: =F13+F11+F9 -> 3039994 | G16: =G13+G11+G9 -> 3322373.9 | H16: =H13+H11+H9 -> 3601275.9 | I16: =I13+I11+I9 -> 3868050.7 | ... M16: =M13+M11+M9 -> 4872552.3
A17: Operating Profit | B17: =B6-B16 -> 351578 | C17: =C6-C16 -> 536495 | D17: =D6-D16 -> 692970 | E17: =E6-E16 -> 758714 | F17: =F6-F16 -> 855537.59 | G17: =G6-G16 -> 935007.02 | H17: =H6-H16 -> 1013497.7 | I17: =I6-I16 -> 1088575.4 | ... M17: =M6-M16 -> 1371269.7
A18: % Change | C18: =C17/B17-1 -> 0.52596294 | D18: =D17/C17-1 -> 0.29166162 | E18: =E17/D17-1 -> 0.094872794 | F18: =F17/E17-1 -> 0.1276154 | G18: =G17/F17-1 -> 0.0928883 | H18: =H17/G17-1 -> 0.083946601 | I18: =I17/H17-1 -> 0.07407787 | J18: =J17/I17-1 -> 0.065267816 | ... M18: =M17/L17-1 -> 0.053518047
A19: Other Operational Income and Expenses | B19: 34951 | C19: -43528 | D19: -13764 | E19: -146626 | F19: 0 | G19: 0 | H19: 0 | I19: 0 | J19: 0 | K19: 0 | L19: 0 | M19: 0
A20: R&D Expense | F20: =-'CapEx Readjustments'!F10 -> -43058.993 | G20: =-'CapEx Readjustments'!G10 -> -47058.67 | H20: =-'CapEx Readjustments'!H10 -> -51009.085 | I20: =-'CapEx Readjustments'!I10 -> -54787.73 | J20: =-'CapEx Readjustments'!J10 -> -58363.605 | K20: =-'CapEx Readjustments'!K10 -> -62121.709 | L20: =-'CapEx Readjustments'!L10 -> -65509.71 | M20: =-'CapEx Readjustments'!M10 -> -69015.662
A21: Operational Profit | B21: =B17+B19 -> 386529 | C21: =C17+C19 -> 492967 | D21: =D17+D19 -> 679206 | E21: =E17+E19 -> 612088 | F21: =F17+F19+F20 -> 812478.6 | G21: =G17+G19+G20 -> 887948.35 | H21: =H17+H19+H20 -> 962488.6 | I21: =I17+I19+I20 -> 1033787.7 | J21: =J17+J19+J20 -> 1101260.8 | K21: =K17+K19+K20 -> 1172172.3 | L21: =L17+L19+L20 -> 1236100.4 | M21: =M17+M19+M20 -> 1302254
A22: % Change | C22: =C21/B21-1 -> 0.27536873 | D22: =D21/C21-1 -> 0.37779202 | E22: =E21/D21-1 -> -0.098818326 | F22: =F21/E21-1 -> 0.32738854 | G22: =G21/F21-1 -> 0.0928883 | H22: =H21/G21-1 -> 0.083946601 | I22: =I21/H21-1 -> 0.07407787 | J22: =J21/I21-1 -> 0.065267816 | ... M22: =M21/L21-1 -> 0.053518047
A23: Financial Result | B23: -62362 | C23: -34864 | D23: -87403 | E23: 19358 | F23: 0 | G23: 0 | H23: 0 | I23: 0 | J23: 0 | K23: 0 | L23: 0 | M23: 0
A24: Result from Associates and Joint Ventures and Impairment of Financial Assets | B24: 28494 | C24: 55621 | D24: 51347 | E24: 61060 | F24: 0 | G24: 0 | H24: 0 | I24: 0 | J24: 0 | K24: 0 | L24: 0 | M24: 0
A25: Profit Before Tax | B25: =B21+B23+B24 -> 352661 | C25: =C21+C23+C24 -> 513724 | D25: =D21+D23+D24 -> 643150 | E25: =E21+E23+E24 -> 692506 | F25: =F21+F23+F24 -> 812478.6 | G25: =G21+G23+G24 -> 887948.35 | H25: =H21+H23+H24 -> 962488.6 | I25: =I21+I23+I24 -> 1033787.7 | ... M25: =M21+M23+M24 -> 1302254
A26: % Change | C26: =C25/B25-1 -> 0.45670772 | D26: =D25/C25-1 -> 0.25193684 | E26: =E25/D25-1 -> 0.07674104 | F26: =F25/E25-1 -> 0.17324413 | G26: =G25/F25-1 -> 0.0928883 | H26: =H25/G25-1 -> 0.083946601 | I26: =I25/H25-1 -> 0.07407787 | J26: =J25/I25-1 -> 0.065267816 | ... M26: =M25/L25-1 -> 0.053518047
A27: Less: Income Tax | B27: 153745 | C27: 101201 | D27: 143262 | E27: 149973 | F27: =F25*F28 -> 203119.65 | G27: =G25*G28 -> 221987.09 | H27: =H25*H28 -> 240622.15 | I27: =I25*I28 -> 258446.93 | J27: =J25*J28 -> 275315.19 | K27: =K25*K28 -> 293043.07 | L27: =L25*L28 -> 309025.09 | M27: =M25*M28 -> 325563.51
A28: Effective Tax Rate | B28: =B27/B25 -> 0.43595691 | C28: =C27/C25 -> 0.19699488 | D28: =D27/D25 -> 0.22275052 | E28: =E27/E25 -> 0.21656563 | F28: 0.25 | G28: 0.25 | H28: 0.25 | I28: 0.25 | J28: 0.25 | K28: 0.25 | L28: 0.25 | M28: 0.25
A29: Net Profit for the Year | B29: =B25-B27 -> 198916 | C29: =C25-C27 -> 412523 | D29: =D25-D27 -> 499888 | E29: =E25-E27 -> 542533 | F29: =F25-F27 -> 609358.95 | G29: =G25-G27 -> 665961.27 | H29: =H25-H27 -> 721866.45 | I29: =I25-I27 -> 775340.78 | ... M29: =M25-M27 -> 976690.53
A30: Less: Non-Controlling Interests | B30: 22123 | C30: -13033 | D30: -34679 | E30: -11884 | F30: 0 | G30: 0 | H30: 0 | I30: 0 | J30: 0 | K30: 0 | L30: 0 | M30: 0
A31: Net Profit Attributable to the Parent Company | B31: =B29+B30 -> 221039 | C31: =C29+C30 -> 399490 | D31: =D29+D30 -> 465209 | E31: =E29+E30 -> 530649 | F31: =F29+F30 -> 609358.95 | G31: =G29+G30 -> 665961.27 | H31: =H29+H30 -> 721866.45 | I31: =I29+I30 -> 775340.78 | ... M31: =M29+M30 -> 976690.53
A32: % Change | C32: =C31/B31-1 -> 0.80732812 | D32: =D31/C31-1 -> 0.16450725 | E32: =E31/D31-1 -> 0.14066796 | F32: =F31/E31-1 -> 0.14832771 | G32: =G31/F31-1 -> 0.0928883 | H32: =H31/G31-1 -> 0.083946601 | I32: =I31/H31-1 -> 0.07407787 | J32: =J31/I31-1 -> 0.065267816 | ... M32: =M31/L31-1 -> 0.053518047
A33: Adjusted Net Profit | F33: =F31+'CapEx Readjustments'!F10-'CapEx Readjustments'!F13 -> 630741.63 | G33: =G31+'CapEx Readjustments'!G10-'CapEx Readjustments'!G13 -> 685997.95 | H33: =H31+'CapEx Readjustments'!H10-'CapEx Readjustments'!H13 -> 740844.38 | I33: =I31+'CapEx Readjustments'!I10-'CapEx Readjustments'!I13 -> 793352.87 | J33: =J31+'CapEx Readjustments'!J10-'CapEx Readjustments'!J13 -> 843030.52 | K33: =K31+'CapEx Readjustments'!K10-'CapEx Readjustments'!K13 -> 895701.03 | L33: =L31+'CapEx Readjustments'!L10-'CapEx Readjustments'!L13 -> 942892.13 | M33: =M31+'CapEx Readjustments'!M10-'CapEx Readjustments'!M13 -> 992059.13
A36: ASSETS
A37: Property, Plant, and Equipment | B37: 210971 | C37: 271094 | D37: 326341 | E37: 380356 | F37: =E37-F119-F92 -> 485774.91 | G37: =F37-G119-G92 -> 583771.48 | H37: =G37-H119-H92 -> 675941.25 | I37: =H37-I119-I92 -> 762922.13 | J37: =I37-J119-J92 -> 845052.24 | K37: =J37-K119-K92 -> 924364.47 | L37: =K37-L119-L92 -> 999841.86 | M37: =L37-M119-M92 -> 1072971
A38: Intangible Assets | B38: 2660758 | C38: 4062277 | D38: 4114267 | E38: 4705720 | F38: =E38-F124-F94 -> 5038849.1 | G38: =F38-G124-G94 -> 5403831.4 | H38: =G38-H124-H94 -> 5799960 | I38: =H38-I124-I94 -> 6225469.5 | J38: =I38-J124-J94 -> 6678340.4 | K38: =J38-K124-K94 -> 7159917.4 | L38: =K38-L124-L94 -> 7666732.3 | M38: =L38-M124-M94 -> 8199589.9
A39: R&D Asset | F39: ='CapEx Readjustments'!F14 -> 108087.93 | G39: ='CapEx Readjustments'!G14 -> 128124.62 | H39: ='CapEx Readjustments'!H14 -> 147102.55 | I39: ='CapEx Readjustments'!I14 -> 165114.64 | J39: ='CapEx Readjustments'!J14 -> 182199.59 | K39: ='CapEx Readjustments'!K14 -> 198771.4 | L39: ='CapEx Readjustments'!L14 -> 214588.26 | M39: ='CapEx Readjustments'!M14 -> 229956.86
A40: Right-of-use Assets | B40: 188653 | C40: 239873 | D40: 287922 | E40: 365076 | F40: =E40-F96 -> 289155 | G40: =F40-G96 -> 229022.49 | H40: =G40-H96 -> 181395.1 | I40: =H40-I96 -> 143672.28 | J40: =I40-J96 -> 113794.27 | K40: =J40-K96 -> 90129.678 | L40: =K40-L96 -> 71386.361 | M40: =L40-M96 -> 56540.893
A41: Investments in Associates and Joint Ventures | B41: 346456 | C41: 344824 | D41: 375212 | E41: 395190 | F41: =E41+F125 -> 395190 | G41: =F41+G125 -> 395190 | H41: =G41+H125 -> 395190 | I41: =H41+I125 -> 395190 | J41: =I41+J125 -> 395190 | K41: =J41+K125 -> 395190 | L41: =K41+L125 -> 395190 | M41: =L41+M125 -> 395190
A42: Financial Investments | B42: 9595 | C42: 14154 | D42: 16359 | E42: 689 | F42: =E42+F123 -> 689 | G42: =F42+G123 -> 689 | H42: =G42+H123 -> 689 | I42: =H42+I123 -> 689 | J42: =I42+J123 -> 689 | K42: =J42+K123 -> 689 | L42: =K42+L123 -> 689 | M42: =L42+M123 -> 689
A43: Other Non-current Assets | B43: 62637 | C43: 102615 | D43: 131444 | E43: 130865 | F43: =E43 -> 130865 | G43: =F43 -> 130865 | H43: =G43 -> 130865 | I43: =H43 -> 130865 | J43: =I43 -> 130865 | K43: =J43 -> 130865 | L43: =K43 -> 130865 | M43: =L43 -> 130865
A44: Deferred Tax Assets | B44: 85066 | C44: 123897 | D44: 146562 | E44: 171826 | F44: =E44 -> 171826 | G44: =F44 -> 171826 | H44: =G44 -> 171826 | I44: =H44 -> 171826 | J44: =I44 -> 171826 | K44: =J44 -> 171826 | L44: =K44 -> 171826 | M44: =L44 -> 171826
A45: Total non-current assets | B45: =SUM(B37:B44) -> 3564136 | C45: =SUM(C37:C44) -> 5158734 | D45: =SUM(D37:D44) -> 5398107 | E45: =SUM(E37:E44) -> 6149722 | F45: =SUM(F37:F44) -> 6620437 | G45: =SUM(G37:G44) -> 7043320 | H45: =SUM(H37:H44) -> 7502968.9 | I45: =SUM(I37:I44) -> 7995748.5 | ... M45: =SUM(M37:M44) -> 10257629
A46: Inventories | B46: 363134 | C46: 626333 | D46: 788866 | E46: 720312 | F46: =F76*F$2/365 -> 841368.18 | G46: =G76*G$2/365 -> 919521.44 | H46: =H76*H$2/365 -> 996712.14 | I46: =I76*I$2/365 -> 1070546.5 | J46: =J76*J$2/365 -> 1140418.7 | K46: =K76*K$2/365 -> 1213851.6 | L46: =L76*L$2/365 -> 1280052.8 | M46: =M76*M$2/365 -> 1348558.7
A47: Trade Accounts Receivable | B47: 317254 | C47: 387936 | D47: 484705 | E47: 567529 | F47: =F77*F$2/365 -> 599329.83 | G47: =G77*G$2/365 -> 655000.56 | H47: =H77*H$2/365 -> 709985.63 | I47: =I77*I$2/365 -> 762579.85 | J47: =J77*J$2/365 -> 812351.77 | K47: =K77*K$2/365 -> 864660.09 | L47: =L77*L$2/365 -> 911817.03 | M47: =M77*M$2/365 -> 960615.69
A48: Other Current Assets | B48: 153664 | C48: 232059 | D48: 186709 | E48: 282991 | F48: =F78*F$2/365 -> 143579.12 | G48: =G78*G$2/365 -> 156915.94 | H48: =H78*H$2/365 -> 170088.5 | I48: =I78*I$2/365 -> 182688.3 | J48: =J78*J$2/365 -> 194611.97 | K48: =K78*K$2/365 -> 207143.27 | L48: =L78*L$2/365 -> 218440.47 | M48: =M78*M$2/365 -> 230130.98
A49: Cash and Cash Equivalents | B49: 692659 | C49: =C140 -> 710050 | D49: =D140 -> 852901 | E49: =E140 -> 882646 | F49: =F140 -> 951538.4 | G49: =G140 -> 983840.6 | H49: =H140 -> 1029598.4 | I49: =I140 -> 1087346.1 | J49: =J140 -> 1156530.9 | ... M49: =M140 -> 1432910.8
A50: Total Current Assets | B50: =SUM(B46:B49) -> 1526711 | C50: =SUM(C46:C49) -> 1956378 | D50: =SUM(D46:D49) -> 2313181 | E50: =SUM(E46:E49) -> 2453478 | F50: =SUM(F46:F49) -> 2535815.5 | G50: =SUM(G46:G49) -> 2715278.5 | H50: =SUM(H46:H49) -> 2906384.6 | I50: =SUM(I46:I49) -> 3103160.7 | ... M50: =SUM(M46:M49) -> 3972216.2
A51: TOTAL ASSETS | B51: =SUM(B50,B45) -> 5090847 | C51: =SUM(C50,C45) -> 7115112 | D51: =SUM(D50,D45) -> 7711288 | E51: =SUM(E50,E45) -> 8603200 | F51: =SUM(F50,F45) -> 9156252.5 | G51: =SUM(G50,G45) -> 9758598.5 | H51: =SUM(H50,H45) -> 10409354 | I51: =SUM(I50,I45) -> 11098909 | ... M51: =SUM(M50,M45) -> 14229845
A53: LIABILITIES
A54: Share Capital | B54: 4203 | C54: 114700 | D54: 144000 | E54: 128499 | F54: =E54+F130 -> 128499 | G54: =F54+G130 -> 128499 | H54: =G54+H130 -> 128499 | I54: =H54+I130 -> 128499 | J54: =I54+J130 -> 128499 | K54: =J54+K130 -> 128499 | L54: =K54+L130 -> 128499 | M54: =L54+M130 -> 128499
A55: Reserves and Retained Earnings | B55: 1127890 | C55: 877796 | D55: 1087933 | E55: 3612174 | F55: =E55+F31+F132 -> 4038725.3 | G55: =F55+G31+G132 -> 4504898.2 | H55: =G55+H31+H132 -> 5010204.7 | I55: =H55+I31+I132 -> 5552943.2 | J55: =I55+J31+J132 -> 6131105.1 | K55: =J55+K31+K132 -> 6746495.6 | L55: =K55+L31+L132 -> 7395448.3 | M55: =L55+M31+M132 -> 8079131.6
A56: Unrealized Gains (losses) Reserve | B56: -8458 | C56: 30255 | D56: 10935 | E56: -27720 | F56: =E56 -> -27720 | G56: =F56 -> -27720 | H56: =G56 -> -27720 | I56: =H56 -> -27720 | J56: =I56 -> -27720 | K56: =J56 -> -27720 | L56: =K56 -> -27720 | M56: =L56 -> -27720
A57: Treasury Shares | B57: 0 | C57: 0 | D57: -105907 | E57: -80281 | F57: =E57 -> -80281 | G57: =F57 -> -80281 | H57: =G57 -> -80281 | I57: =H57 -> -80281 | J57: =I57 -> -80281 | K57: =J57 -> -80281 | L57: =K57 -> -80281 | M57: =L57 -> -80281
A58: Interim Dividend | B58: 0 | C58: 0 | D58: -80000 | E58: 0 | F58: 0 | G58: 0 | H58: 0 | I58: 0 | J58: 0 | K58: 0 | L58: 0 | M58: 0
A59: Cumulative Translation Adjustment | B59: -83220 | C59: -77902 | D59: -107055 | E59: -106568 | F59: =E59 -> -106568 | G59: =F59 -> -106568 | H59: =G59 -> -106568 | I59: =H59 -> -106568 | J59: =I59 -> -106568 | K59: =J59 -> -106568 | L59: =K59 -> -106568 | M59: =L59 -> -106568
A60: R&D Asset Adjustment | F60: ='CapEx Readjustments'!F14 -> 108087.93 | G60: ='CapEx Readjustments'!G14 -> 128124.62 | H60: ='CapEx Readjustments'!H14 -> 147102.55 | I60: ='CapEx Readjustments'!I14 -> 165114.64 | J60: ='CapEx Readjustments'!J14 -> 182199.59 | K60: ='CapEx Readjustments'!K14 -> 198771.4 | L60: ='CapEx Readjustments'!L14 -> 214588.26 | M60: ='CapEx Readjustments'!M14 -> 229956.86
A61: Equity attributable to the Parent Company | B61: =SUM(B54:B59) -> 1040415 | C61: =SUM(C54:C59) -> 944849 | D61: =SUM(D54:D59) -> 949906 | E61: =SUM(E54:E59) -> 3526104 | F61: =SUM(F54:F60) -> 4060743.2 | G61: =SUM(G54:G60) -> 4546952.8 | H61: =SUM(H54:H60) -> 5071237.2 | I61: =SUM(I54:I60) -> 5631987.9 | J61: =SUM(J54:J60) -> 6227234.7 | K61: =SUM(K54:K60) -> 6859197 | L61: =SUM(L54:L60) -> 7523966.5 | M61: =SUM(M54:M60) -> 8223018.5
A62: Non-controlling Interests | B62: 8068 | C62: 6748 | D62: 9303 | E62: 11580 | F62: =E62 -> 11580 | G62: =F62 -> 11580 | H62: =G62 -> 11580 | I62: =H62 -> 11580 | J62: =I62 -> 11580 | K62: =J62 -> 11580 | L62: =K62 -> 11580 | M62: =L62 -> 11580
A63: Total Equity | B63: =SUM(B61:B62) -> 1048483 | C63: =SUM(C61:C62) -> 951597 | D63: =SUM(D61:D62) -> 959209 | E63: =SUM(E61:E62) -> 3537684 | F63: =SUM(F61:F62) -> 4072323.2 | G63: =SUM(G61:G62) -> 4558532.8 | H63: =SUM(H61:H62) -> 5082817.2 | I63: =SUM(I61:I62) -> 5643567.9 | ... M63: =SUM(M61:M62) -> 8234598.5
A64: Non-current Bank Borrowings | B64: 826606 | C64: 1662311 | D64: 1788846 | E64: 1129931 | F64: =E64+F135 -> 1054010 | G64: =F64+G135 -> 993877.49 | H64: =G64+H135 -> 946250.1 | I64: =H64+I135 -> 908527.28 | J64: =I64+J135 -> 878649.27 | K64: =J64+K135 -> 854984.68 | L64: =K64+L135 -> 836241.36 | M64: =L64+M135 -> 821395.89
A65: Deferred Tax Liabilities | B65: 398852 | C65: 552629 | D65: 553741 | E65: 619128 | F65: =E65 -> 619128 | G65: =F65 -> 619128 | H65: =G65 -> 619128 | I65: =H65 -> 619128 | J65: =I65 -> 619128 | K65: =J65 -> 619128 | L65: =K65 -> 619128 | M65: =L65 -> 619128
A66: Provisions and Other Liabilities | B66: 1844186 | C66: 2753941 | D66: 2759606 | E66: 1513147 | F66: =E66 -> 1513147 | G66: =F66 -> 1513147 | H66: =G66 -> 1513147 | I66: =H66 -> 1513147 | J66: =I66 -> 1513147 | K66: =J66 -> 1513147 | L66: =K66 -> 1513147 | M66: =L66 -> 1513147
A67: Total Non-current Liabilities | B67: =SUM(B64:B66) -> 3069644 | C67: =SUM(C64:C66) -> 4968881 | D67: =SUM(D64:D66) -> 5102193 | E67: =SUM(E64:E66) -> 3262206 | F67: =SUM(F64:F66) -> 3186285 | G67: =SUM(G64:G66) -> 3126152.5 | H67: =SUM(H64:H66) -> 3078525.1 | I67: =SUM(I64:I66) -> 3040802.3 | ... M67: =SUM(M64:M66) -> 2953670.9
A68: Current Bank Borrowings | B68: 145987 | C68: 177001 | D68: 358371 | E68: 527173 | F68: =F79*F$2/365 -> 388323.43 | G68: =G79*G$2/365 -> 424394.14 | H68: =H79*H$2/365 -> 460020.58 | I68: =I79*I$2/365 -> 494097.93 | J68: =J79*J$2/365 -> 526346.62 | K68: =K79*K$2/365 -> 560238.72 | L68: =L79*L$2/365 -> 590793.08 | M68: =M79*M$2/365 -> 622411.18
A69: Trade Accounts Payable | B69: 166542 | C69: 238887 | D69: 212072 | E69: 229492 | F69: =F80*F4/365 -> 287474.2 | G69: =G80*G4/365 -> 314177.19 | H69: =H80*H4/365 -> 340551.3 | I69: =I80*I4/365 -> 365778.61 | J69: =J80*J4/365 -> 389652.18 | K69: =K80*K4/365 -> 414742.36 | L69: =L80*L4/365 -> 437361.63 | M69: =M80*M4/365 -> 460768.37
A70: Other Current Liabilities | B70: 641993 | C70: 749650 | D70: 1024124 | E70: 999020 | F70: =F81*F$2/365 -> 1172608.8 | G70: =G81*G$2/365 -> 1281530.4 | H70: =H81*H$2/365 -> 1389110.5 | I70: =I81*I$2/365 -> 1492012.9 | J70: =J81*J$2/365 -> 1589393.3 | K70: =K81*K$2/365 -> 1691736.3 | L70: =L81*L$2/365 -> 1784000.4 | M70: =M81*M$2/365 -> 1879476.6
A71: Income Tax | B71: 18198 | C71: 29096 | D71: 55319 | E71: 47625 | F71: =F82*F$2/365 -> 49237.874 | G71: =G82*G$2/365 -> 53811.496 | H71: =H82*H$2/365 -> 58328.788 | I71: =I82*I$2/365 -> 62649.661 | J71: =J82*J$2/365 -> 66738.667 | K71: =K82*K$2/365 -> 71036.051 | L71: =L82*L$2/365 -> 74910.224 | M71: =M82*M$2/365 -> 78919.273
A72: Total Current Liabilities | B72: =SUM(B68:B71) -> 972720 | C72: =SUM(C68:C71) -> 1194634 | D72: =SUM(D68:D71) -> 1649886 | E72: =SUM(E68:E71) -> 1803310 | F72: =SUM(F68:F71) -> 1897644.3 | G72: =SUM(G68:G71) -> 2073913.2 | H72: =SUM(H68:H71) -> 2248011.2 | I72: =SUM(I68:I71) -> 2414539.1 | ... M72: =SUM(M68:M71) -> 3041575.4
A73: TOTAL LIABILITIES AND EQUITY | B73: =B63+B67+B72 -> 5090847 | C73: =C63+C67+C72 -> 7115112 | D73: =D63+D67+D72 -> 7711288 | E73: =E63+E67+E72 -> 8603200 | F73: =F63+F67+F72 -> 9156252.5 | G73: =G63+G67+G72 -> 9758598.5 | H73: =H63+H67+H72 -> 10409354 | I73: =I63+I67+I72 -> 11098909 | ... M73: =M63+M67+M72 -> 14229845
A75: Turnover Ratios in days
A76: Inventory in days | B76: =B46/B2*365 -> 51.274002 | C76: =C46/C2*365 -> 63.159287 | D76: =D46/D2*365 -> 66.898608 | E76: =E46/E2*365 -> 54.890608 | F76: =AVERAGE(B76:E76) -> 59.055626 | G76: =F76 -> 59.055626 | H76: =G76 -> 59.055626 | I76: =H76 -> 59.055626 | J76: =I76 -> 59.055626 | K76: =J76 -> 59.055626 | L76: =K76 -> 59.055626 | M76: =L76 -> 59.055626
A77: Debtor days | B77: =B47/B2*365 -> 44.795811 | C77: =C47/C2*365 -> 39.119384 | D77: =D47/D2*365 -> 41.104687 | E77: =E47/E2*365 -> 43.247942 | F77: =AVERAGE(B77:E77) -> 42.066956 | G77: =F77 -> 42.066956 | H77: =G77 -> 42.066956 | I77: =H77 -> 42.066956 | J77: =I77 -> 42.066956 | K77: =J77 -> 42.066956 | L77: =K77 -> 42.066956 | M77: =L77 -> 42.066956
A78: Other Current Assets | B78: =B43/B2*365 -> 8.8442549 | C78: =C43/C2*365 -> 10.347675 | D78: =D43/D2*365 -> 11.146913 | E78: =E43/E2*365 -> 9.9724277 | F78: =AVERAGE(B78:E78) -> 10.077818 | G78: =F78 -> 10.077818 | H78: =G78 -> 10.077818 | I78: =H78 -> 10.077818 | J78: =I78 -> 10.077818 | K78: =J78 -> 10.077818 | L78: =K78 -> 10.077818 | M78: =L78 -> 10.077818
A79: Current Bank Borrowings | B79: =B68/B2*365 -> 20.613156 | C79: =C68/C2*365 -> 17.848743 | D79: =D68/D2*365 -> 30.39112 | E79: =E68/E2*365 -> 40.172656 | F79: =AVERAGE(B79:E79) -> 27.256419 | G79: =F79 -> 27.256419 | H79: =G79 -> 27.256419 | I79: =H79 -> 27.256419 | J79: =I79 -> 27.256419 | K79: =J79 -> 27.256419 | L79: =K79 -> 27.256419 | M79: =L79 -> 27.256419
A80: Trade Accounts Payable | B80: =B69/B4*365 -> 86.85142 | C80: =C69/C4*365 -> 94.063291 | D80: =D69/D4*365 -> 71.086413 | E80: =E69/E4*365 -> 69.706286 | F80: =AVERAGE(B80:E80) -> 80.426853 | G80: =F80 -> 80.426853 | H80: =G80 -> 80.426853 | I80: =H80 -> 80.426853 | J80: =I80 -> 80.426853 | K80: =J80 -> 80.426853 | L80: =K80 -> 80.426853 | M80: =L80 -> 80.426853
A81: Other Current Liabilities | B81: =B70/B2*365 -> 90.648494 | C81: =C70/C2*365 -> 75.594547 | D81: =D70/D2*365 -> 86.849313 | E81: =E70/E2*365 -> 76.129254 | F81: =AVERAGE(B81:E81) -> 82.305402 | G81: =F81 -> 82.305402 | H81: =G81 -> 82.305402 | I81: =H81 -> 82.305402 | J81: =I81 -> 82.305402 | K81: =J81 -> 82.305402 | L81: =K81 -> 82.305402 | M81: =L81 -> 82.305402
A82: Income Tax | B82: =B71/B2*365 -> 2.5695316 | C82: =C71/C2*365 -> 2.9340345 | D82: =D71/D2*365 -> 4.6912455 | E82: =E71/E2*365 -> 3.6292123 | F82: =AVERAGE(B82:E82) -> 3.456006 | G82: =F82 -> 3.456006 | H82: =G82 -> 3.456006 | I82: =H82 -> 3.456006 | J82: =I82 -> 3.456006 | K82: =J82 -> 3.456006 | L82: =K82 -> 3.456006 | M82: =L82 -> 3.456006
A84: Balance Sheet Check | B84: =B51-B73 -> 0 | C84: =C51-C73 -> 0 | D84: =D51-D73 -> 0 | E84: =E51-E73 -> 0 | F84: =F51-F73 -> 0 | G84: =G51-G73 -> 0 | H84: =H51-H73 -> 0 | I84: =I51-I73 -> 0 | ... M84: =M51-M73 -> 0
A87: Cash Flows from Operating activities
A88: Profit / (loss) attributable to the Parent Company | B88: =B31 -> 221039 | C88: =C31 -> 399490 | D88: =D31 -> 465209 | E88: =E31 -> 530649 | F88: =F33 -> 630741.63 | G88: =G33 -> 685997.95 | H88: =H33 -> 740844.38 | I88: =I33 -> 793352.87 | J88: =J33 -> 843030.52 | K88: =K33 -> 895701.03 | L88: =L33 -> 942892.13 | M88: =M33 -> 992059.13
A89: Profit / (loss) attributable to non-controlling interests | B89: -22123 | C89: 13033 | D89: 34679 | E89: 11884 | F89: =F30 -> 0 | G89: =G30 -> 0 | H89: =H30 -> 0 | I89: =I30 -> 0 | J89: =J30 -> 0 | K89: =K30 -> 0 | L89: =L30 -> 0 | M89: =M30 -> 0
A90: Elimination of expenses and income with no impact on cash flows:
A91: Depreciation and Amortization
A92: Depreciation and impairment of property, plant and equipment | B92: 49886 | C92: 64248 | D92: 70975 | E92: 93420 | F92: =F93*E37 -> 93420 | G92: =G93*F37 -> 119312.15 | H92: =H93*G37 -> 143381.29 | I92: =I93*H37 -> 166019.29 | J92: =J93*I37 -> 187382.84 | K92: =K93*J37 -> 207554.97 | L92: =L93*K37 -> 227035.01 | M92: =M93*L37 -> 245573.16
A93: % of Property, Plants and Equipments | B93: =B92/B37 -> 0.23645904 | C93: =C92/C37 -> 0.23699529 | D93: =D92/D37 -> 0.21748723 | E93: =E92/E37 -> 0.24561201 | F93: =E93 -> 0.24561201 | G93: =F93 -> 0.24561201 | H93: =G93 -> 0.24561201 | I93: =H93 -> 0.24561201 | J93: =I93 -> 0.24561201 | K93: =J93 -> 0.24561201 | L93: =K93 -> 0.24561201 | M93: =L93 -> 0.24561201
A94: Depreciation and impairment of intangible assets | B94: 19567 | C94: 26966 | D94: 32903 | E94: 41154 | F94: =F95*E38 -> 41154 | G94: =G95*F38 -> 44067.39 | H94: =H95*G38 -> 47259.352 | I94: =I95*H38 -> 50723.705 | J94: =J95*I38 -> 54445.01 | K94: =K95*J38 -> 58405.604 | L94: =L95*K38 -> 62617.249 | M94: =M95*L38 -> 67049.613
A95: % of intangible assets | B95: =B94/B38 -> 0.0073539194 | C95: =C94/C38 -> 0.006638149 | D95: =D94/D38 -> 0.0079972933 | E95: =E94/E38 -> 0.0087455267 | F95: =E95 -> 0.0087455267 | G95: =F95 -> 0.0087455267 | H95: =G95 -> 0.0087455267 | I95: =H95 -> 0.0087455267 | J95: =I95 -> 0.0087455267 | K95: =J95 -> 0.0087455267 | L95: =K95 -> 0.0087455267 | M95: =L95 -> 0.0087455267
A96: Depreciation and impairment of right-of-use assets | B96: 37071 | C96: 53739 | D96: 65826 | E96: 75921 | F96: =F97*E40 -> 75921 | G96: =G97*F40 -> 60132.511 | H96: =H97*G40 -> 47627.388 | I96: =I97*H40 -> 37722.823 | J96: =J97*I40 -> 29878.006 | K96: =K97*J40 -> 23664.593 | L96: =L97*K40 -> 18743.317 | M96: =M97*L40 -> 14845.468
A97: % of right-of-use assets | B97: =B96/B40 -> 0.19650363 | C97: =C96/C40 -> 0.22403105 | D97: =D96/D40 -> 0.22862442 | E97: =E96/E40 -> 0.20795944 | F97: =E97 -> 0.20795944 | G97: =F97 -> 0.20795944 | H97: =G97 -> 0.20795944 | I97: =H97 -> 0.20795944 | J97: =I97 -> 0.20795944 | K97: =J97 -> 0.20795944 | L97: =K97 -> 0.20795944 | M97: =L97 -> 0.20795944
A98: Amortization of R&D Asset | F98: ='CapEx Readjustments'!F13 -> 21676.312 | G98: ='CapEx Readjustments'!G13 -> 27021.983 | H98: ='CapEx Readjustments'!H13 -> 32031.155 | I98: ='CapEx Readjustments'!I13 -> 36775.637 | J98: ='CapEx Readjustments'!J13 -> 41278.66 | K98: ='CapEx Readjustments'!K13 -> 45549.897 | L98: ='CapEx Readjustments'!L13 -> 49692.85 | M98: ='CapEx Readjustments'!M13 -> 53647.065
A99: Total Depreciation and amortization | B99: =B96+B94+B92 -> 106524 | C99: =C96+C94+C92 -> 144953 | D99: =D96+D94+D92 -> 169704 | E99: =E96+E94+E92 -> 210495 | F99: =F96+F94+F92+F98 -> 232171.31 | G99: =G96+G94+G92+G98 -> 250534.03 | H99: =H96+H94+H92+H98 -> 270299.18 | I99: =I96+I94+I92+I98 -> 291241.45 | J99: =J96+J94+J92+J98 -> 312984.51 | K99: =K96+K94+K92+K98 -> 335175.07 | L99: =L96+L94+L92+L98 -> 358088.43 | M99: =M96+M94+M92+M98 -> 381115.31
A100: Deferred Tax Expense / Income | B100: 67892 | C100: -32774 | D100: -19370 | E100: -20283 | F100: 0 | G100: 0 | H100: 0 | I100: 0 | J100: 0 | K100: 0 | L100: 0 | M100: 0
A101: Other Financial Income / Expenses | B101: 1300 | C101: 3024 | D101: 5098 | E101: 8868 | F101: 0 | G101: 0 | H101: 0 | I101: 0 | J101: 0 | K101: 0 | L101: 0 | M101: 0
A102: Financial Expenses | B102: 25570 | C102: 29968 | D102: 54364 | E102: 58217 | F102: 0 | G102: 0 | H102: 0 | I102: 0 | J102: 0 | K102: 0 | L102: 0 | M102: 0
A103: Other Adjustments | B103: 16435 | C103: 17340 | D103: 26223 | E103: -15314 | F103: 0 | G103: 0 | H103: 0 | I103: 0 | J103: 0 | K103: 0 | L103: 0 | M103: 0
A104: Capital Gains and Losses on Disposals of Assets | B104: 32 | C104: 69 | D104: -457 | E104: 668 | F104: 0 | G104: 0 | H104: 0 | I104: 0 | J104: 0 | K104: 0 | L104: 0 | M104: 0
A105: Other Non-Current Assets and Liabilities | B105: 55407 | C105: 58676 | D105: 66787 | E105: -25663 | F105: 0 | G105: 0 | H105: 0 | I105: 0 | J105: 0 | K105: 0 | L105: 0 | M105: 0
A106: Profit / (Loss) from Associates and Joint Ventures | B106: -28494 | C106: -55621 | D106: -51347 | E106: -61060 | F106: 0 | G106: 0 | H106: 0 | I106: 0 | J106: 0 | K106: 0 | L106: 0 | M106: 0
A107: Gross Cash Flow | B107: =SUM(B99:B106)+B89+B88 -> 443582 | C107: =SUM(C99:C106)+C89+C88 -> 578158 | D107: =SUM(D99:D106)+D89+D88 -> 750890 | E107: =SUM(E99:E106)+E89+E88 -> 698461 | F107: =SUM(F99:F106)+F89+F88 -> 862912.94 | G107: =SUM(G99:G106)+G89+G88 -> 936531.99 | H107: =SUM(H99:H106)+H89+H88 -> 1011143.6 | I107: =SUM(I99:I106)+I89+I88 -> 1084594.3 | ... M107: =SUM(M99:M106)+M89+M88 -> 1373174.4
A108: Changes in Working Capital
...

Sheet CapEx Readjustments
C1: Assumed Life (in Years) | E1: 4
B2: 2021 | C2: 2022 | D2: 2023 | E2: 2024 | F2: 2025 | G2: 2026 | H2: 2027 | I2: 2028 | J2: 2029 | K2: 2030 | L2: 2031 | M2: 2032
A3: Acquisitions Normalization
A4: Acquisition Expense | B4: =-'Financial Statements'!B124 -> -4368 | C4: =-'Financial Statements'!C124 -> 840189 | D4: =-'Financial Statements'!D124 -> 0 | E4: =-'Financial Statements'!E124 -> 265288 | F4: =F5*'Revenue Prediction'!F2 -> 374283.12 | G4: =G5*'Revenue Prediction'!G2 -> 409049.64 | H4: =H5*'Revenue Prediction'!H2 -> 443387.97 | I4: =I5*'Revenue Prediction'!I2 -> 476233.2 | J4: =J5*'Revenue Prediction'!J2 -> 507315.9 | K4: =K5*'Revenue Prediction'!K2 -> 539982.59 | L4: =L5*'Revenue Prediction'!L2 -> 569432.23 | M4: =M5*'Revenue Prediction'!M2 -> 599907.13
A5: % of Revenue | B5: =B4/'Financial Statements'!B2 -> -0.0016897407 | C5: =C4/'Financial Statements'!C2 -> 0.23212187 | D5: =D4/'Financial Statements'!D2 -> 0 | E5: =E4/'Financial Statements'!E2 -> 0.055386271 | F5: =AVERAGE(B4:E4)/AVERAGE('Revenue Prediction'!B2:E2) -> 0.071975148 | G5: =F5 -> 0.071975148 | H5: =G5 -> 0.071975148 | I5: =H5 -> 0.071975148 | J5: =I5 -> 0.071975148 | K5: =J5 -> 0.071975148 | L5: =K5 -> 0.071975148 | M5: =L5 -> 0.071975148
A6: Amortization of Acquisition | B6: ='Financial Statements'!B94 -> 19567 | C6: ='Financial Statements'!C94 -> 26966 | D6: ='Financial Statements'!D94 -> 32903 | E6: ='Financial Statements'!E94 -> 41154 | F6: =F4*F7 -> 3244.9244 | G6: =G4*G7 -> 3546.3399 | H6: =H4*H7 -> 3844.0431 | I6: =I4*I7 -> 4128.8017 | J6: =J4*J7 -> 4398.2795 | K6: =K4*K7 -> 4681.4901 | L6: =L4*L7 -> 4936.8098 | M6: =M4*M7 -> 5201.0182
A7: Amortization % | B7: =B6/(B6+'Financial Statements'!B38) -> 0.0073002341 | C7: =C6/(C6+'Financial Statements'!C38) -> 0.0065943746 | D7: =D6/(D6+'Financial Statements'!D38) -> 0.007933844 | E7: =E6/(E6+'Financial Statements'!E38) -> 0.0086697056 | F7: =E7 -> 0.0086697056 | G7: =F7 -> 0.0086697056 | H7: =G7 -> 0.0086697056 | I7: =H7 -> 0.0086697056 | J7: =I7 -> 0.0086697056 | K7: =J7 -> 0.0086697056 | L7: =K7 -> 0.0086697056 | M7: =L7 -> 0.0086697056
B9: -4 | C9: -3 | D9: -2 | E9: -1 | F9: 0
A10: R&D Expense | B10: 22677 | C10: 28592 | D10: 33208 | E10: 41834 | F10: ='Revenue Prediction'!F2*'CapEx Readjustments'!F11 -> 43058.993 | G10: ='Revenue Prediction'!G2*'CapEx Readjustments'!G11 -> 47058.67 | H10: ='Revenue Prediction'!H2*'CapEx Readjustments'!H11 -> 51009.085 | I10: ='Revenue Prediction'!I2*'CapEx Readjustments'!I11 -> 54787.73 | J10: ='Revenue Prediction'!J2*'CapEx Readjustments'!J11 -> 58363.605 | K10: ='Revenue Prediction'!K2*'CapEx Readjustments'!K11 -> 62121.709 | L10: ='Revenue Prediction'!L2*'CapEx Readjustments'!L11 -> 65509.71 | M10: ='Revenue Prediction'!M2*'CapEx Readjustments'!M11 -> 69015.662
A11: % of Revenue | B11: =B10/'Financial Statements'!B2 -> 0.0087724931 | C11: =C10/'Financial Statements'!C2 -> 0.0078992088 | D11: =D10/'Financial Statements'!D2 -> 0.0077154933 | E11: =E10/'Financial Statements'!E2 -> 0.0087340147 | F11: =AVERAGE(B11:E11) -> 0.0082803025 | G11: =F11 -> 0.0082803025 | H11: =G11 -> 0.0082803025 | I11: =H11 -> 0.0082803025 | J11: =I11 -> 0.0082803025 | K11: =J11 -> 0.0082803025 | L11: =K11 -> 0.0082803025 | M11: =L11 -> 0.0082803025
A12: Unamortized at Beginning of 0 | B12: =B10*(1-(3/4)) -> 5669.25 | C12: =C10*(1-(2/4)) -> 14296 | D12: =D10*(1-(1/4)) -> 24906 | E12: =E10 -> 41834 | F12: =SUM(B12:E12) -> 86705.25 | G12: =F14 -> 108087.93 | H12: =G14 -> 128124.62 | I12: =H14 -> 147102.55 | J12: =I14 -> 165114.64 | K12: =J14 -> 182199.59 | L12: =K14 -> 198771.4 | M12: =L14 -> 214588.26
A13: Amortization | F13: =F12/4 -> 21676.312 | G13: =G12/4 -> 27021.983 | H13: =H12/4 -> 32031.155 | I13: =I12/4 -> 36775.637 | J13: =J12/4 -> 41278.66 | K13: =K12/4 -> 45549.897 | L13: =L12/4 -> 49692.85 | M13: =M12/4 -> 53647.065
A14: Unamortized at End of Year | F14: =F12-F13+F10 -> 108087.93 | G14: =G12-G13+G10 -> 128124.62 | H14: =H12-H13+H10 -> 147102.55 | I14: =I12-I13+I10 -> 165114.64 | J14: =J12-J13+J10 -> 182199.59 | K14: =K12-K13+K10 -> 198771.4 | L14: =L12-L13+L10 -> 214588.26 | M14: =M12-M13+M10 -> 229956.86
A15: Capex | F15: =F10-F13 -> 21382.681 | G15: =G10-G13 -> 20036.687 | H15: =H10-H13 -> 18977.931 | I15: =I10-I13 -> 18012.092 | J15: =J10-J13 -> 17084.945 | K15: =K10-K13 -> 16571.812 | L15: =L10-L13 -> 15816.86 | M15: =M10-M13 -> 15368.597
M17: Historical Data
M18: Assumptions
M20: All figures in million euros

Sheet Beta
A1: Source - Beta | B1: Bloomberg | D1: Tax rate | E1: 0.25
A2: Source - Financials | B2: Yahoo Finance
A5: ELF Beauty Inc | B5: 2024 | C5: 2023 | D5: 2022 | E5: 2021 | G5: Unlevered Beta | H5: Business Beta | I5: Operating Asset Beta
A7: Revenue | B7: 1313517 | C7: 1023932 | D7: 578844 | E7: 392155
A8: Operating Profit | B8: 158027 | C8: 149678 | D8: 68143 | E8: 29820
A9: Change in Operating Income % | B9: =B8/C8-1 -> 0.055779741 | C9: =C8/D8-1 -> 1.1965279 | D9: =D8/E8-1 -> 1.2851442
A10: Change in Revenue % | B10: =B7/C7-1 -> 0.28281663 | C10: =C7/D7-1 -> 0.76892565 | D10: =D7/E7-1 -> 0.47605921
A11: Operating Leverage | B11: =AVERAGE(B9:D9)/AVERAGE(B10:D10) -> 1.6608518
A13: Market Cap | B13: 6670000
A14: Debt | B14: 313018
A15: Cash | B15: 148692
A16: Beta | B16: 1.51 | G16: =B16/(1+(B14/B13)*(1-$E$1)) -> 1.4586597 | H16: =G16/B11 -> 0.87825999 | I16: =H16/(1-(B15/(B14+B13))) -> 0.89736798
A19: Proya Cosmetics | B19: Currency | C19: CNY
A21: Revenue | B21: 10778412 | C21: 8904573.5 | D21: 6385451.4 | E21: 4633150.5
A22: Operating Profit | B22: 1958959 | C22: 1580285.3 | D22: 1192128.6 | E22: 749666.62
A23: % Change Operating Profit | B23: =B22/C22-1 -> 0.23962363 | C23: =C22/D22-1 -> 0.32559967 | D23: =D22/E22-1 -> 0.59021167
A24: % Change Revenue | B24: =B21/C21-1 -> 0.21043549 | C24: =C21/D21-1 -> 0.39450963 | D24: =D21/E21-1 -> 0.37820936
A25: Operating Leverage | B25: =AVERAGE(B23:D23)/AVERAGE(B24:D24) -> 1.1752324
A27: Market Cap | B27: 32857000
A28: Debt | B28: 794440.48
A29: Cash | B29: 4082126.4
A30: Beta | B30: 0.31 | G30: =B30/(1+(B28/B27)*(1-$E$1)) -> 0.30447857 | H30: =G30/B25 -> 0.25907946 | I30: =H30/(1-(B29/(B28+B27))) -> 0.2948461
A32: Coty INC CLA
A34: Revenue | B34: 6118000 | C34: 5554100 | D34: 5304400 | E34: 4629900
A35: Operating Income | B35: 583400 | C35: 537200 | D35: 280500 | E35: 153800
A36: % Change Operating Income | B36: =B35/C35-1 -> 0.086001489 | C36: =C35/D35-1 -> 0.91515152 | D36: =D35/E35-1 -> 0.82379714
A37: % Change Revenue | B37: =B34/C34-1 -> 0.1015286 | C37: =C34/D34-1 -> 0.047074127 | D37: =D34/E34-1 -> 0.14568349
A38: Operating Leverage | B38: =AVERAGE(B36:D36)/AVERAGE(B37:D37) -> 6.2012762
A40: Market CAP | B40: 4313000
A41: Debt | B41: 4121300
A42: Cash | B42: 300800
A43: Beta | B43: 1.9 | G43: =B43/(1+(B41/B40)*(1-$E$1)) -> 1.1067974 | H43: =G43/B38 -> 0.17847896 | I43: =H43/(1-(B42/(B41+B40))) -> 0.18507962
A45: Interparfums US
A46: Revenue | B46: 1452325 | C46: 1317675 | D46: 1086653 | E46: 879516
A47: Operating Income | B47: 278801 | C47: 251382 | D47: 202052 | E47: 150443
A48: % Change Operating Income | B48: =B47/C47-1 -> 0.10907304 | C48: =C47/D47-1 -> 0.24414507 | D48: =D47/E47-1 -> 0.34304687
A49: % Change Revenue | B49: =B46/C46-1 -> 0.10218757 | C49: =C46/D46-1 -> 0.21259961 | D49: =D46/E46-1 -> 0.23551249
A50: Operating Leverage | B50: =AVERAGE(B48:D48)/AVERAGE(B49:D49) -> 1.265247
A52: Market Cap | B52: 4156000
A53: Debt | B53: 192194
A54: Cash | B54: 234744
A55: Beta | B55: 1.38 | G55: =B55/(1+(B53/B52)*(1-$E$1)) -> 1.3337409 | H55: =G55/B50 -> 1.0541348 | I55: =H55/(1-(B54/(B53+B52))) -> 1.1142916
A57: Kose Corporation
A58: Revenue | B58: 322758000 | C58: 300406000 | D58: 289136000 | E58: 279389000
A59: Operating Income | B59: 17368000 | C59: 15989000 | D59: 22124000 | E59: 13296000
A60: % Change in Operating Income | B60: =B59/C59-1 -> 0.086246795 | C60: =C59/D59-1 -> -0.27730067 | D60: =D59/E59-1 -> 0.66395909
A61: % Change in Revenue | B61: =B58/C58-1 -> 0.074405971 | C61: =C58/D58-1 -> 0.038978197 | D61: =D58/E58-1 -> 0.034886842
A62: Operating Leverage | B62: =AVERAGE(B60:D60)/AVERAGE(B61:D61) -> 3.1894651
A64: Market Cap | B64: 314256000
A65: Debt | B65: 11222000
A66: Cash | B66: 113970000
A67: Beta | B67: 0.22 | G67: =B67/(1+(B65/B64)*(1-$E$1)) -> 0.21426158 | H67: =G67/B62 -> 0.067177904 | I67: =H67/(1-(B66/(B65+B64))) -> 0.10337637
A69: LVMH
A70: Revenue | B70: 84683000 | C70: 86153000 | D70: 79183000 | E70: 64215000
A71: Operating Income | B71: 19578000 | C71: 22781000 | D71: 21014000 | E71: 17122000
A72: % Change in Operating Income | B72: =B71/C71-1 -> -0.14059962 | C72: =C71/D71-1 -> 0.084086799 | D72: =D71/E71-1 -> 0.22730989
A73: % Change in Revenue | B73: =B70/C70-1 -> -0.017062668 | C73: =C70/D70-1 -> 0.088023945 | D73: =D70/E70-1 -> 0.23309196
A74: Operating Leverage | B74: =AVERAGE(B72:D72)/AVERAGE(B73:D73) -> 0.5617341
A76: Market Cap | B76: 236769000
A77: Debt | B77: 41203000
A78: Cash | B78: 13587000
A79: Beta | B79: 1 | G79: =B79/(1+(B77/B76)*(1-$E$1)) -> 0.88455148 | H79: =G79/B74 -> 1.57468 | I79: =H79/(1-(B78/(B77+B76))) -> 1.6556044
A82: Estee Lauder
A83: Revenue | B83: 15608000 | C83: 15910000 | D83: 17737000 | E83: 16215000
A84: Operating Income | B84: 1563000 | C84: 1771000 | D84: 3544000 | E84: 3010000
A85: % Change in Operating Income | B85: =B84/C84-1 -> -0.11744777 | C85: =C84/D84-1 -> -0.50028217 | D85: =D84/E84-1 -> 0.17740864
A86: % Change in Revenue | B86: =B83/C83-1 -> -0.018981772 | C86: =C83/D83-1 -> -0.10300502 | D86: =D83/E83-1 -> 0.093863706
A87: Operating Leverage | B87: =AVERAGE(B85:D85)/AVERAGE(B86:D86) -> 15.656935
A89: Market Cap | B89: 31329000
A90: Debt | B90: 9826000
A91: Cash | B91: 3395000
A92: Beta | B92: 1.12 | G92: =B92/(1+(B90/B89)*(1-$E$1)) -> 0.90671421 | H92: =G92/B87 -> 0.057911348 | I92: =H92/(1-(B91/(B90+B89))) -> 0.063118154
A95: Puig Brands, SA
A96: Revenue | B96: 4789779 | C96: 4304067 | D96: 3619603 | E96: 2585012
A97: Operating Income | B97: 749386 | C97: 688513 | D97: 536495 | E97: 386529
A98: % Change in Operating Income | B98: =B97/C97-1 -> 0.088412274 | C98: =C97/D97-1 -> 0.28335399 | D98: =D97/E97-1 -> 0.38798124
A99: % Change in Revenue | B99: =B96/C96-1 -> 0.11284954 | C99: =C96/D96-1 -> 0.18909919 | D99: =D96/E96-1 -> 0.40022677
A100: Operating Leverage | B100: =AVERAGE(B98:D98)/AVERAGE(B99:D99) -> 1.0819909
A102: Market Cap | B102: 9588000
A103: Debt | B103: 1731605
A104: Cash | B104: 884435
A106: Puig Beta Calculations
A107: Operating Asset Beta | B107: =AVERAGE(I16:I89) -> 0.70842767
A108: Business Beta | B108: =B107*(1-(B104/(B103+B102))) -> 0.65307607 | C108: =AVERAGE(H16:H92) -> 0.58138893
A109: Unlevered Beta | B109: =B108*B100 -> 0.70662237 | C109: =C108*B100 -> 0.62905753
A110: Levered Beta for Puig | B110: =B109*(1+($B$103/$B$102)*(1-$E$1)) -> 0.80233504 | C110: =C109*(1+($B$103/$B$102)*(1-$E$1)) -> 0.71426398

Sheet Mature MRP
A1: ROE is estimated
A2: Discount Rate | B2: 0.07989265 | C2: Rm
A3: Government Bond Yield | B3: 0.02716 | C3: Source: https://www.investing.com/rates-bonds/germany-10-year-bond-yield
A5: Measure | B5: 0 | C5: 1 | D5: 2 | E5: 3
A6: Earnings Per Share | B6: 1312.63 | C6: 1479.55 | D6: 1667.66 | E6: 1896.3 | F6: =E6*(1+F9) -> 1947.8794
A7: Book Value Per Share | B7: 11943.75 | C7: 13030.39 | D7: 14000.37 | E7: 14832.72
A8: ROE Estimated | C8: =C6/B7 -> 0.1238765 | D8: =D6/C7 -> 0.12798236 | E8: =E6/D7 -> 0.13544642 | F8: =AVERAGE(C8:E8) -> 0.12910176
A9: Growth | C9: =C6/B6-1 -> 0.12716455 | D9: =D6/C6-1 -> 0.12714001 | E9: =E6/D6-1 -> 0.13710229 | F9: 0.0272 | G9: 0.0272
A10: Equity Reinvestment rate | C10: =D9/C8 -> 1.0263448 | D10: =E9/D8 -> 1.0712593 | E10: =F9/E8 -> 0.20081741 | F10: =G9/F8 -> 0.21068652
A11: FCFE | C11: =C6*(1-C10) -> -38.97848 | D11: =D6*(1-D10) -> -118.83627 | E11: =E6*(1-E10) -> 1515.4899 | F11: =F6*(1-F10) -> 1537.4874
A12: Terminal Value | E12: =F11/(B2-B3) -> 29156.271
A13: Cash flow | C13: =SUM(C11:C12) -> -38.97848 | D13: =SUM(D11:D12) -> -118.83627 | E13: =SUM(E11:E12) -> 30671.761
A14: Present value of future FCFE | C14: =C13/((1+$B$2)^C5) -> -36.094773 | D14: =D13/((1+$B$2)^D5) -> -101.9032 | E14: =E13/((1+$B$2)^E5) -> 24355.495
A15: NPV | B15: =SUM(C14:E14) -> 24217.497
A16: Index Value | B16: 24217.5
H17: Historical Data
A18: MMRP | B18: =B2-B3 -> 0.05273265 | H18: Assumptions

Sheet Geography CRP & Lambda
A1: Country | B1: GDP (in Millions)
A2: Angola | B2: 84722.958 | C2: 30456.567
A3: Benin | B3: 19673.285 | C3: 4047.3638 | G3: GDP | H3: Exports | I3: Exports to GDP Ratio | J3: Average Domestic Consumption | K3: Puig Regional Revenue % | L3: Lambda | M3: CRP | N3: Weight of GDP | O3: CRP * Weight
A4: Botswana | B4: 19395.765 | C4: 5053.3186 | F4: Africa | G4: 2349249.4 | H4: 639236.34 | M4: =VLOOKUP(F4,'[1]Damodaran CRP by Country'!$A$2:$E$167,3,0) -> 0.02359997 | N4: =G4/$G$8 -> 0.076820708 | O4: =M4*N4 -> 0.0018129664
A5: Burkina Faso | B5: 20324.618 | C5: 6623.3648 | F5: Middle East | G5: 3109419.4 | H5: 1613802.7 | M5: =VLOOKUP(F5,'[1]Damodaran CRP by Country'!$A$2:$E$167,3,0) -> 0.023271353 | N5: =G5/$G$8 -> 0.10167835 | O5: =M5*N5 -> 0.0023661927
A6: Cameroon | B6: 47945.51 | C6: 7564.1228 | F6: Eastern Europe | G6: 3172972.5 | H6: 1762405.7 | M6: =VLOOKUP(F6,'[1]Damodaran CRP by Country'!$A$2:$E$167,3,0) -> 0.037600057 | N6: =G6/$G$8 -> 0.10375654 | O6: =M6*N6 -> 0.0039012519
A7: Cape Verde | B7: 1936 | C7: 917.99624 | F7: Western Europe | G7: 21949298 | H7: 10708723 | M7: =VLOOKUP(F7,'[1]Damodaran CRP by Country'!$A$2:$E$167,3,0) -> 0.012240226 | N7: =G7/$G$8 -> 0.7177444 | O7: =M7*N7 -> 0.008785354
A8: Congo (Democratic Republic of) | B8: 66383.287 | C8: 32984.602 | F8: EMEA | G8: =SUM(G4:G7) -> 30580939 | H8: =SUM(H4:H7) -> 14724168 | I8: =H8/G8 -> 0.48148187 | J8: =1-I8 -> 0.51851813 | K8: =AVERAGE('Revenue Prediction'!F16:M16) -> 0.54710347 | L8: =K8/J8 -> 1.0551289 | M8: =SUM(O4:O7) -> 0.016865765
A9: Congo (Republic of) | B9: 15321.056 | C9: 8296.9525 | F9: Central and South America | G9: 6318352.5 | H9: 1660027.6 | M9: =VLOOKUP(F9,'[1]Damodaran CRP by Country'!$A$2:$E$167,3,0) -> 0.050924919 | N9: =G9/$G$12 -> 0.17467531 | O9: =M9*N9 -> 0.0088953261
A10: Côte d'Ivoire | B10: 78788.829 | C10: 23882.966 | F10: North America | G10: 29501021 | H10: 3907781.7 | M10: =VLOOKUP(F10,'[1]Damodaran CRP by Country'!$A$2:$E$167,3,0) -> 0.0037403298 | N10: =G10/$G$12 -> 0.81557652 | O10: =M10*N10 -> 0.0030505251
A11: Egypt | B11: 395926.08 | C11: 79983.635 | F11: Caribbean | G11: 352610.57 | H11: 75906.469 | M11: =VLOOKUP(F11,'[1]Damodaran CRP by Country'!$A$2:$E$167,3,0) -> 0.089534906 | N11: =G11/$G$12 -> 0.0097481679 | O11: =M11*N11 -> 0.0008728013
A12: Ethiopia | B12: 163697.93 | C12: 10451.092 | F12: Americas | G12: =SUM(G9:G11) -> 36171984 | H12: =SUM(H9:H11) -> 5643715.8 | I12: =H12/G12 -> 0.1560245 | J12: =1-I12 -> 0.8439755 | K12: =AVERAGE('Revenue Prediction'!F17:M17) -> 0.34502624 | L12: =K12/J12 -> 0.40881073 | M12: =SUM(O9:O11) -> 0.012818653
A13: Gabon | B13: 20516.134 | C13: 13621.52 | F13: Asia | G13: 33158417 | H13: 9887824.9 | M13: =VLOOKUP(F13,'[1]Damodaran CRP by Country'!$A$2:$E$167,3,0) -> 0.017068463 | N13: =G13/$G$15 -> 0.94368614 | O13: =M13*N13 -> 0.016107272
A14: Ghana | B14: 76370.394 | C14: 29197.466 | F14: Australia & New Zealand | G14: 1978706.9 | H14: 493583.29 | M14: =VLOOKUP(F14,'[1]Damodaran CRP by Country'!$A$2:$E$167,3,0) -> 4.758694e-05 | N14: =G14/$G$15 -> 0.056313856 | O14: =M14*N14 -> 2.6798041e-06
A15: Kenya | B15: 107440.58 | C15: 13865.029 | F15: APAC | G15: =SUM(G13:G14) -> 35137123 | H15: =SUM(H13:H14) -> 10381408 | I15: =H15/G15 -> 0.29545413 | J15: =1-I15 -> 0.70454587 | K15: =AVERAGE('Revenue Prediction'!F18:M18) -> 0.10787029 | L15: =K15/J15 -> 0.15310613 | M15: =SUM(O13:O14) -> 0.016109952
A16: Mali | B16: 20904.898 | C16: 5986.892
A17: Mauritius | B17: 14397.127 | C17: 6908.9787
A18: Morocco | B18: 141109.37 | C18: 66846.859
A19: Mozambique | B19: 20624.598 | C19: 9579.5494
A20: Namibia | B20: 12351.025 | C20: 5568.7655
A21: Niger | B21: 16819.17 | C21: 6086.7484
A22: Nigeria | B22: 362814.95 | C22: 64001.156
A23: Rwanda | B23: 14097.769 | C23: 4392.6526
A24: Senegal | B24: 31013.986 | C24: 9053.0821
A25: South Africa | B25: 377781.6 | C25: 127482.42
A26: Swaziland | B26: 4597.8558 | C26: 2137
A27: Tanzania | B27: 79158.286 | C27: 15622.428
... A31: Zambia | B31: 28162.631 | C31: 11264.526
A32: Africa | B32: =SUM(B2:B31) -> 2349249.4 | C32: =SUM(C2:C31) -> 639236.34
A33: Bangladesh | B33: 437415.33 | C33: 47087.839
A34: Cambodia | B34: 31772.76 | C34: 33078.91
A35: China | B35: 17794782 | C35: 3753056.1
A36: Fiji | B36: 5494.7975 | C36: 3100.1389
A37: Hong Kong | B37: 382054.57 | C37: 660362.37
A38: India | B38: 3549918.9 | C38: 828633.46
A39: Indonesia | B39: 1371171.2 | C39: 309745.62
A40: Japan | B40: 4212945.2 | C40: 920644.08
A41: Korea | B41: 1712792.9 | C41: 570645.71
A42: Laos | B42: 15843.156 | C42: 2218
A43: Macao | B43: 47061.844 | C43: 536.128
A44: Malaysia | B44: 399648.83 | C44: 301096.58
... A56: Vietnam | B56: 429716.97 | C56: 366131.32
A57: Asia | B57: =SUM(B33:B56) -> 33158417 | C57: =SUM(C33:C56) -> 9887824.9
A58: Australia | B58: 1723827.2 | C58: 432883.02
A59: Cook Islands | B59: 1414 | C59: 180.74332
A60: New Zealand | B60: 253465.7 | C60: 60519.518
A61: Australia & New Zealand | B61: =SUM(B58:B60) -> 1978706.9 | C61: =SUM(C58:C60) -> 493583.29
A62: Aruba | B62: 3544.7078 | C62: 3223.2877
A63: Bahamas | B63: 11210 | C63: 689
A64: Barbados | B64: 6393.5642 | C64: 1707.2403
A65: Bermuda | B65: 7827.98 | C65: 5056.8
A66: Cayman Islands | B66: 6600.844 | C66: 3372.4935
A67: Cuba | B67: 107351 | C67: 8768.5
A68: Curacao | B68: 3073.8403 | C68: 8843.8085
A69: Dominican Republic | B69: 121444.28 | C69: 28296.491
A70: Jamaica | B70: 19423.355 | C70: 6642.9219
A71: Montserrat | B71: 16199 | C71: 22.08524
A72: St. Maarten | B72: 11900 | C72: 903.65512
A73: St. Vincent & the Grenadines | B73: 8100 | C73: 373.80659
... A75: Turks and Caicos Islands | B75: 1402.0544 | C75: 682.1533
A76: Caribbean | B76: =SUM(B62:B75) -> 352610.57 | C76: =SUM(C62:C75) -> 75906.469
A77: Argentina | B77: 640591.41 | C77: 97106.595
A78: Belize | B78: 3281.5 | C78: 1695.7253
A79: Bolivia | B79: 45849.833 | C79: 11524.078
A80: Brazil | B80: 2173665.7 | C80: 392614.11
A81: Chile | B81: 335533.33 | C81: 111377.05
A82: Colombia | B82: 363540.16 | C82: 66852.964
A83: Costa Rica | B83: 86497.941 | C83: 36740.229
A84: Ecuador | B84: 118844.83 | C84: 37750.171
A85: El Salvador | B85: 34015.62 | C85: 11585.81
A86: Guatemala | B86: 102050.47 | C86: 17990.664
A87: Honduras | B87: 34400.51 | C87: 12444.558
A88: Mexico | B88: 1788886.8 | C88: 681537.9
... A95: Venezuela | B95: 98400 | C95: 10025.391
A96: Central and South America | B96: =SUM(B77:B95) -> 6318352.5 | C96: =SUM(C77:C95) -> 1660027.6
A97: Albania | B97: 22977.678 | C97: 9813.7613
A98: Armenia | B98: 24212.135 | C98: 19687.315
A99: Azerbaijan | B99: 72356.176 | C99: 34112.882
A100: Belarus | B100: 71857.383 | C100: 49423.786
A101: Bosnia and Herzegovina | B101: 27054.889 | C101: 12136.912
A102: Bulgaria | B102: 101584.38 | C102: 62622.308
A103: Croatia | B103: 82688.843 | C103: 46077.395
A104: Czech Republic | B104: 330858.34 | C104: 196747.31
A105: Estonia | B105: 40744.849 | C105: 32617.706
A106: Georgia | B106: 30535.53 | C106: 16335.737
A107: Hungary | B107: 212388.91 | C107: 166429.2
A108: Kazakhstan | B108: 261421.12 | C108: 90360.13
... A122: Uzbekistan | B122: 90889.149 | C122: 26172.759
A123: Eastern Europe | B123: =SUM(B97:B122) -> 3172972.5 | C123: =SUM(C97:C122) -> 1762405.7
A124: Abu Dhabi | B124: 310000 | C124: 29360
A125: Bahrain | B125: 43205 | C125: 40349.468
A126: Iraq | B126: 250842.78 | C126: 104886.43
A127: Israel | B127: 509901.5 | C127: 153655.74
A128: Jordan | B128: 50813.642 | C128: 22734.507
A129: Kuwait | B129: 11000 | C129: 110924.41
A130: Lebanon | B130: 17937.256 | C130: 6134.302
A131: Oman | B131: 108192.46 | C131: 64749.025
A132: Qatar | B132: 235770.4 | C132: 161692.86
A133: Saudi Arabia | B133: 1067582.9 | C133: 360914.4
A134: United Arab Emirates | B134: 504173.45 | C134: 558401.54
...

Sheet Damodaran CRP by Country
A1: Country | B1: GDP (in Millions) | C1: Country Risk Premium | D1: GDP Weight
A2: Angola | B2: 84722.958 | C2: 0.032513421 | D2: 0.036063841 | E2: =D2*C2 -> 0.0011725589
A3: Benin | B3: 19673.285 | C3: 0.023646125 | D3: 0.0083742852 | E3: =D3*C3 -> 0.00019801939
A4: Botswana | B4: 19395.765 | C4: 0.0073024796 | D4: 0.008256154 | E4: =D4*C4 -> 6.0290397e-05
A5: Burkina Faso | B5: 20324.618 | D5: 0.0086515368 | E5: =D5*C5 -> 0
A6: Cameroon | B6: 47945.51 | D6: 0.020408863 | E6: =D6*C6 -> 0
A7: Cape Verde | B7: 1936 | C7: 0.028166707 | D7: 0.000824093 | E7: =D7*C7 -> 2.3211986e-05
A8: Congo (Democratic Republic of) | B8: 66383.287 | C8: 0.032513421 | D8: 0.028257232 | E8: =D8*C8 -> 0.0009187393
A9: Congo (Republic of) | B9: 15321.056 | D9: 0.0065216812 | E9: =D9*C9 -> 0
A10: Côte d'Ivoire | B10: 78788.829 | C10: 0.044510352 | D10: 0.033537873 | E10: =D10*C10 -> 0.0014927825
A11: Egypt | B11: 395926.08 | D11: 0.16853301 | E11: =D11*C11 -> 0
A12: Ethiopia | B12: 163697.93 | D12: 0.069680948 | E12: =D12*C12 -> 0
A13: Gabon | B13: 20516.134 | D13: 0.0087330592 | E13: =D13*C13 -> 0
A14: Ghana | B14: 76370.394 | D14: 0.032508423 | E14: =D14*C14 -> 0
A15: Kenya | B15: 107440.58 | D15: 0.045734001 | E15: =D15*C15 -> 0
A16: Mali | B16: 20904.898 | D16: 0.0088985435 | E16: =D16*C16 -> 0
A17: Mauritius | B17: 14397.127 | C17: 0.096149315 | D17: 0.0061283945 | E17: =D17*C17 -> 0.00058924094
A18: Morocco | B18: 141109.37 | C18: 0.037034004 | D18: 0.060065726 | E18: =D18*C18 -> 0.0022244743
A19: Mozambique | B19: 20624.598 | C19: 0.14796215 | D19: 0.0087792286 | E19: =D19*C19 -> 0.0012989935
A20: Namibia | B20: 12351.025 | C20: 0.023646125 | D20: 0.0052574344 | E20: =D20*C20 -> 0.00012431795
A21: Niger | B21: 16819.17 | C21: 0.14796215 | D21: 0.0071593805 | E21: =D21*C21 -> 0.0010593173
A22: Nigeria | B22: 362814.95 | C22: 0.032513421 | D22: 0.15443867 | E22: =D22*C22 -> 0.0050213295
A23: Rwanda | B23: 14097.769 | C23: 0.028166707 | D23: 0.0060009672 | E23: =D23*C23 -> 0.00016902748
A24: Senegal | B24: 31013.986 | C24: 0.032513421 | D24: 0.013201658 | E24: =D24*C24 -> 0.00042923105
A25: South Africa | B25: 377781.6 | C25: 0.044510352 | D25: 0.16080949 | E25: =D25*C25 -> 0.007157687
A26: Swaziland | B26: 4597.8558 | C26: 0.028166707 | D26: 0.0019571595 | E26: =D26*C26 -> 5.5126739e-05
A27: Tanzania | B27: 79158.286 | C27: 0.023646125 | D27: 0.033695139 | E27: =D27*C27 -> 0.00079675946
A28: Togo | B28: 9171.2618 | C28: 0.032513421 | D28: 0.0039039115 | E28: =D28*C28 -> 0.00012692952
A29: Tunisia | B29: 48529.595 | D29: 0.02065749 | E29: =D29*C29 -> 0
A30: Uganda | B30: 49272.882 | C30: 0.032513421 | D30: 0.020973883 | E30: =D30*C30 -> 0.00068193269
A31: Zambia | B31: 28162.631 | D31: 0.011987927 | E31: =D31*C31 -> 0
A32: Africa | B32: 2349249.4 | C32: =SUM(E2:E31) -> 0.02359997 | D32: 1 | E32: =D32*C32 -> 0.02359997
A33: Bangladesh | B33: 437415.33 | C33: 0.081370487 | D33: 0.013191683 | E33: =D33*C33 -> 0.0010734137
A34: Cambodia | B34: 31772.76 | C34: 0.081370487 | D34: 0.00095821102 | E34: =D34*C34 -> 7.7970097e-05
A35: China | B35: 17794782 | C35: 0.010432114 | D35: 0.53665958 | E35: =D35*C35 -> 0.0055984938
A36: Fiji | B36: 5494.7975 | C36: 0.06659166 | D36: 0.00016571351 | E36: =D36*C36 -> 1.1035138e-05
A37: Hong Kong | B37: 382054.57 | C37: 0.0088672967 | D37: 0.011522099 | E37: =D37*C37 -> 0.00010216987
A38: India | B38: 3549918.9 | C38: 0.032513421 | D38: 0.10705936 | E38: =D38*C38 -> 0.0034808661
A39: Indonesia | B39: 1371171.2 | C39: 0.028166707 | D39: 0.04135213 | E39: =D39*C39 -> 0.0011647533
A40: Japan | B40: 4212945.2 | C40: 0.010432114 | D40: 0.12705508 | E40: =D40*C40 -> 0.001325453
A41: Korea | B41: 1712792.9 | C41: 0.0073024796 | D41: 0.051654845 | E41: =D41*C41 -> 0.00037720845
A42: Laos | B42: 15843.156 | C42: 0.14796215 | D42: 0.00047780194 | E42: =D42*C42 -> 7.0696601e-05
A43: Macao | B43: 47061.844 | C43: 0.0088672967 | D43: 0.0014193031 | E43: =D43*C43 -> 1.2585382e-05
A44: Malaysia | B44: 399648.83 | C44: 0.017734593 | D44: 0.012052712 | E44: =D44*C44 -> 0.00021374994
... A56: Vietnam | B56: 429716.97 | C56: 0.044510352 | D56: 0.012959514 | E56: =D56*C56 -> 0.00057683254
A57: Asia | B57: 33158417 | C57: =SUM(E33:E56) -> 0.017068463 | D57: 1 | E57: =D57*C57 -> 0.017068463
A58: Australia | B58: 1723827.2 | C58: 0 | D58: 0.87118875 | E58: =D58*C58 -> 0
A59: Cook Islands | B59: 1414 | C59: 0.06659166 | D59: 0.0007146081 | E59: =D59*C59 -> 4.758694e-05
A60: New Zealand | B60: 253465.7 | C60: 0 | D60: 0.12809664 | E60: =D60*C60 -> 0
A61: Australia & New Zealand | B61: 1978706.9 | C61: 4.758694e-05 | D61: 1 | E61: =D61*C61 -> 4.758694e-05
A62: Aruba | B62: 3544.7078 | C62: 0.032513421 | D62: 0.010052755 | E62: =D62*C62 -> 0.00032684947
A63: Bahamas | B63: 11210 | C63: 0.06659166 | D63: 0.031791446 | E63: =D63*C63 -> 0.0021170452
A64: Barbados | B64: 6393.5642 | C64: 0.081370487 | D64: 0.018132083 | E64: =D64*C64 -> 0.0014754164
A65: Bermuda | B65: 7827.98 | C65: 0.012518537 | D65: 0.022200072 | E65: =D65*C65 -> 0.00027791241
A66: Cayman Islands | B66: 6600.844 | C66: 0.0088672967 | D66: 0.018719927 | E66: =D66*C66 -> 0.00016599514
A67: Cuba | B67: 107351 | C67: 0.1775198 | D67: 0.30444635 | E67: =D67*C67 -> 0.054045255
A68: Curacao | B68: 3073.8403 | C68: 0.032513421 | D68: 0.00871738 | E68: =D68*C68 -> 0.00028343185
A69: Dominican Republic | B69: 121444.28 | C69: 0.05320378 | D69: 0.34441474 | E69: =D69*C69 -> 0.018324166
... A167: Western Europe | B167: 21964999 | C167: 0.012240226 | D167: 1 | E167: =D167*C167 -> 0.012240226
A170: Region | B170: Weighted Average: ERP | C170: Total GDP | D170: Weight*CRP
A171: =A32 -> Africa | B171: =E32 -> 0.02359997 | C171: 2349249.4 | D171: #N/A
A172: =A57 -> Asia | B172: =E57 -> 0.017068463 | C172: 33158417 | D172: 0.0055518404
A173: =A61 -> Australia & New Zealand | B173: =E61 -> 4.758694e-05 | C173: 1978706.9 | D173: 9.2367253e-07
A174: =A76 -> Caribbean | B174: =E76 -> 0.089534906 | C174: 352610.57 | D174: 0.00030969664
A175: =A96 -> Central and South America | B175: =E96 -> 0.050924919 | C175: 6318352.5 | D175: 0.0031563342
A176: =A123 -> Eastern Europe | B176: =E123 -> 0.037600057 | C176: 3172972.5 | D176: 0.0011703172
A177: =A137 -> Middle East | B177: =E137 -> 0.023271353 | C177: 3145219.4 | D177: 0.00071799489
A178: =A140 -> North America | B178: =E140 -> 0.0037403298 | C178: 29501021 | D178: 0.0010824198
A179: =A167 -> Western Europe | B179: =E167 -> 0.012240226 | C179: 21964999 | D179: 0.00263736
A180: Global | B180: =SUM(H171:H179) -> 0 | C180: 1.0194155e+08 | D180: #N/A
B183: ERP
A184: Africa & Mid East | B184: =(B171*F171+B177*F177)/(F171+F177) -> #DIV/0!
A185: Australia, NZ & Canada | B185: =(B173*F173+E138*B138)/(F173+B138) -> 0
A186: Latin America & Caribbean | B186: =B175*(F175/(F175+F174))+B174*F174/(F174+F175) -> #DIV/0!
A187: Japan | B187: =E40 -> 0.001325453
A188: US | B188: =E139 -> 0.0037403298
A189: Europe | B189: =E167 -> 0.012240226
A190: Emerging Markets | B190: =(B171*F171+B172*F172+B174*F174+B175*F175+B176*F176+B177*F177-B187*B41)/(F171+F172+F174+F175+F176+F177-B41) -> 0.001325453
A191: Small Asia (No India, China & Japan) | B191: =(B172*F172-B35*E35-B38*E38-B40*E40)/(F172-(B35+B38+B40)) -> 0.0045999866
A192: India | B192: =E38 -> 0.0034808661
A193: China | B193: =E35 -> 0.0055984938
A194: Global | B194: =B180 -> 0
B197: ERP
A198: EMEA | B198: =(B179*F179+B177*F177+B171*F171)/(F171+F177+F179) -> #DIV/0!

Sheet WACC
A1: Spain Risk-free Rate
A2: Germany 10 Year Bund Yield | B2: 0.0272 | C2: Source: https://www.investing.com/rates-bonds/germany-10-year-bond-yield | E2: Debt | F2: ='Financial Statements'!E68+'Financial Statements'!E64 -> 1657104
A3: Adjusted default spread | E3: Equity | F3: ='Financial Statements'!F54+'Financial Statements'!E55+'Financial Statements'!E60 -> 3740673
A4: Moody's Rating | B4: Baa1 | E4: D+E | F4: =F3+F2 -> 5397777
A5: Associated Adjusted default spread | B5: 0.0158 | C5: Source: https://pages.stern.nyu.edu/~adamodar/New_Home_Page/datafile/ctryprem.html | E5: Tax Rate | F5: 0.25
A6: Risk-free Rate | B6: =B5+B2 -> 0.043
E7: Wacc | F7: =(F3/F4*B18)+(F2/F4*B24*(1-F5)) -> 0.090262332
A8: Cost of Equity Calculation
A9: Rf | B9: =B6 -> 0.043
A10: MMRP | B10: ='Mature MRP'!B18 -> 0.05273265
A11: Beta | B11: =Beta!B110 -> 0.80233504
A12: EMEA CRP | B12: ='Geography CRP & Lambda'!M8 -> 0.016865765
A13: EMEA Lambda | B13: ='Geography CRP & Lambda'!L8 -> 1.0551289
A14: Americas CRP | B14: ='Geography CRP & Lambda'!M12 -> 0.012818653
A15: Americas Lambda | B15: ='Geography CRP & Lambda'!L12 -> 0.40881073
A16: APAC CRP | B16: ='Geography CRP & Lambda'!M15 -> 0.016109952
A17: APAC Lambda | B17: ='Geography CRP & Lambda'!L15 -> 0.15310613
A18: Cost of Equity | B18: =B9+(B11*B10)+(B13*B12)+(B15*B14)+(B17*B16) -> 0.11081174
A20: Cost of Debt
A21: Moody's Rating | B21: Baa1
A22: Associated Default risk | B22: 0.0155 | C22: source: https://pages.stern.nyu.edu/~adamodar/New_Home_Page/datafile/ratings.html
A23: Rf | B23: =B6 -> 0.043
A24: Cost of Debt | B24: =B23+B22 -> 0.0585
